anglo/__init__.py
anglo/app.py
anglo/constants.py
anglo/request.py
anglo/response.py
anglo/session.py
anglo/utils.py
anglo/debug/__init__.py
anglo/debug/reloader.py
anglo/handlers/__init__.py
anglo/handlers/caching.py
anglo/handlers/file.py
anglo/middleware/__init__.py
anglo/middleware/_session.py
anglo/middleware/routing.py
anglo/routing/__init__.py
anglo/routing/errors.py
anglo/routing/route.py
anglo/routing/router.py
anglo/routing/utils.py
anglo/server/__init__.py
anglo/server/server.py
anglo/server/serving.py
anglo-0.0.1b0.dist-info/LICENSE
anglo-0.0.1b0.dist-info/METADATA
anglo-0.0.1b0.dist-info/WHEEL
anglo-0.0.1b0.dist-info/top_level.txt
anglo-0.0.1b0.dist-info/RECORD
