Metadata-Version: 2.1
Name: anglo
Version: 0.0.1b0
Summary: 🪐 A modern lightweight micro web framework for Python 3.
Home-page: UNKNOWN
Author: Serum Studio
License: MIT
Platform: UNKNOWN
Requires-Dist: hypecli[standard]
